dompare/__init__.py
dompare-0.2.2.dist-info/LICENSE
dompare-0.2.2.dist-info/METADATA
dompare-0.2.2.dist-info/WHEEL
dompare-0.2.2.dist-info/entry_points.txt
dompare-0.2.2.dist-info/top_level.txt
dompare-0.2.2.dist-info/RECORD
