Metadata-Version: 2.1
Name: dompare
Version: 0.2.2
Summary: A program to diff two directories recursively
Home-page: https://github.com/vra/dompare
Author: Yunfeng Wang
Author-email: wyf.brz@gmail.com
License: MIT Licence
Keywords: dompare,Linux,diff,directories
Platform: any
License-File: LICENSE
Requires-Dist: binaryornot (>=0.4.4)
Requires-Dist: loguru
